pats/__init__.py
pats/buyer.py
pats/core.py
pats/seller.py
pats/test_core.py
pats-0.3.dist-info/DESCRIPTION.rst
pats-0.3.dist-info/METADATA
pats-0.3.dist-info/RECORD
pats-0.3.dist-info/WHEEL
pats-0.3.dist-info/metadata.json
pats-0.3.dist-info/top_level.txt
