Metadata-Version: 2.0
Name: pats
Version: 0.3
Summary: Client for the PATS API (www.pats.org.uk)
Home-page: https://github.com/bquinn/pats-api-python
Author: Brendan Quinn
Author-email: brendan@cluefulmedia.com
License: UNKNOWN
Download-URL: https://github.com/bquinn/pats-api-python/archive/0.3.tar.gz
Keywords: api,publishing,advertising
Platform: UNKNOWN
Classifier: Development Status :: 4 - Beta
Classifier: Intended Audience :: Developers
Classifier: License :: OSI Approved :: MIT License
Classifier: Programming Language :: Python :: 3
